mcp_todoist-0.5.1.dist-info/licenses/LICENSE
tests/__init__.py
tests/test_basic.py
tests/test_sdk_inspect.py
tests/test_todoist_api.py
mcp_todoist-0.5.1.dist-info/METADATA
mcp_todoist-0.5.1.dist-info/WHEEL
mcp_todoist-0.5.1.dist-info/top_level.txt
mcp_todoist-0.5.1.dist-info/RECORD
