Metadata-Version: 2.4
Name: mcp-todoist
Version: 0.5.1
Summary: Todoist integration for MCP
Home-page: https://github.com/stevengonsalvez/mcp-todoist
Author: 
Author-email: steven gonsalvez <steven.gonsalvez@gmail.com>
License: MIT
Requires-Python: >=3.10
License-File: LICENSE
Dynamic: home-page
Dynamic: license-file
Dynamic: requires-python
